python_control_flow/__init__.py
python_control_flow/__main__.py
python_control_flow/augment_disasm-nogood.py
python_control_flow/augment_disasm.py
python_control_flow/bb.py
python_control_flow/build_control_flow.py
python_control_flow/cfg.py
python_control_flow/dominators.py
python_control_flow/dotio.py
python_control_flow/graph.py
python_control_flow/traversals.py
python_control_flow/version.py
python_control_flow-1.0.0.dist-info/licenses/LICENSE
python_control_flow-1.0.0.dist-info/METADATA
python_control_flow-1.0.0.dist-info/WHEEL
python_control_flow-1.0.0.dist-info/entry_points.txt
python_control_flow-1.0.0.dist-info/top_level.txt
python_control_flow-1.0.0.dist-info/RECORD
