Metadata-Version: 2.4
Name: python-control-flow
Version: 1.0.0
Summary: Python Bytecode Control Flow Toolkit
Author-email: Rocky Bernstein <rb@dustyfeet.com>
License-Expression: MIT
Project-URL: Homepage, https://github.com/rocky/python-control-flow
Project-URL: Downloads, https://github.com/rocky/python-control-flow/releases
Keywords: Python bytecode,bytecode,disassembler
Classifier: Development Status :: 3 - Alpha
Classifier: Intended Audience :: Developers
Classifier: Programming Language :: Python
Classifier: Topic :: Software Development :: Libraries :: Python Modules
Classifier: Programming Language :: Python :: 3.8
Classifier: Programming Language :: Python :: 3.9
Classifier: Programming Language :: Python :: 3.10
Classifier: Programming Language :: Python :: 3.11
Classifier: Programming Language :: Python :: 3.12
Classifier: Programming Language :: Python :: 3.13
Classifier: Topic :: Software Development :: Code Generators
License-File: LICENSE
Requires-Dist: click
Requires-Dist: xdis<6.3.0,>=6.1.1
Provides-Extra: dev
Requires-Dist: pre-commit; extra == "dev"
Requires-Dist: black; extra == "dev"
Requires-Dist: isort; extra == "dev"
Requires-Dist: pytest; extra == "dev"
Dynamic: license-file
